<archimate:ArchimateDiagramModel
    xmlns:xsi="http://www.w3.org/2001/XMLSchema-instance"
    xmlns:archimate="http://www.archimatetool.com/archimate"
    name="Retail Operations UAT environment (Phase 2)"
    id="f6a1719b-25e8-4b76-bf41-b57d39fb9899">
  <children
      xsi:type="archimate:DiagramModelArchimateObject"
      id="2f42f6e7-7e09-42c7-9d64-26f3170066d9">
    <bounds
        x="24"
        y="24"
        width="300"
        height="253"/>
    <children
        xsi:type="archimate:DiagramModelNote"
        id="a95b4ce9-461a-4ade-b8c4-14f9e28ee8f0"
        textAlignment="1"
        content="AFBS-VRS-RETAPP&#xD;&#xA;&#xD;&#xA;">
      <bounds
          x="24"
          y="48"
          width="109"
          height="34"/>
    </children>
    <children
        xsi:type="archimate:DiagramModelNote"
        id="e6fe8daf-f2ac-4bb0-bc0a-3e35d5b2d4ab"
        textAlignment="1"
        content="10.2.2.177">
      <bounds
          x="156"
          y="48"
          width="109"
          height="34"/>
    </children>
    <children
        xsi:type="archimate:DiagramModelArchimateObject"
        id="d5beed24-7089-4281-954a-c14d9557a9de">
      <bounds
          x="24"
          y="96"
          width="109"
          height="37"/>
      <archimateElement
          xsi:type="archimate:SystemSoftware"
          href="SystemSoftware_4059a0da-88ba-4cee-bc0a-b8e325d833dd.xml#4059a0da-88ba-4cee-bc0a-b8e325d833dd"/>
    </children>
    <children
        xsi:type="archimate:DiagramModelArchimateObject"
        id="491b6506-c0fd-491c-88ab-66b23af9a292"
        type="1">
      <bounds
          x="157"
          y="96"
          width="108"
          height="37"/>
      <archimateElement
          xsi:type="archimate:ApplicationComponent"
          href="ApplicationComponent_2ed6e320-6e41-4b34-9f32-464914acab4e.xml#2ed6e320-6e41-4b34-9f32-464914acab4e"/>
    </children>
    <children
        xsi:type="archimate:DiagramModelArchimateObject"
        id="aa3b51a4-1cae-4527-ad80-304044df5235"
        type="1">
      <bounds
          x="157"
          y="144"
          width="108"
          height="37"/>
      <archimateElement
          xsi:type="archimate:ApplicationComponent"
          href="ApplicationComponent_693a481a-d58e-4940-b6b7-8dbeb69cbf81.xml#693a481a-d58e-4940-b6b7-8dbeb69cbf81"/>
    </children>
    <children
        xsi:type="archimate:DiagramModelArchimateObject"
        id="add1a88c-d480-4816-8632-feabc4be32da"
        type="1">
      <bounds
          x="25"
          y="144"
          width="108"
          height="37"/>
      <archimateElement
          xsi:type="archimate:ApplicationComponent"
          href="ApplicationComponent_03f5e49a-3f74-4b63-84d6-e33bd25383c9.xml#03f5e49a-3f74-4b63-84d6-e33bd25383c9"/>
    </children>
    <children
        xsi:type="archimate:DiagramModelArchimateObject"
        id="40f2a033-bd72-4595-97ef-c711d3561c70"
        type="1">
      <bounds
          x="157"
          y="192"
          width="108"
          height="37"/>
      <archimateElement
          xsi:type="archimate:ApplicationComponent"
          href="ApplicationComponent_cc023a0d-515a-4f7c-a2b2-43dd4381e2b5.xml#cc023a0d-515a-4f7c-a2b2-43dd4381e2b5"/>
    </children>
    <children
        xsi:type="archimate:DiagramModelArchimateObject"
        id="be27a481-485d-436d-9d77-dfeb0bdb4982"
        type="1">
      <bounds
          x="25"
          y="192"
          width="108"
          height="37"/>
      <archimateElement
          xsi:type="archimate:ApplicationComponent"
          href="ApplicationComponent_2b49e14e-7d2d-4b74-b2e1-a4353b7ff752.xml#2b49e14e-7d2d-4b74-b2e1-a4353b7ff752"/>
    </children>
    <archimateElement
        xsi:type="archimate:Node"
        href="Node_96ce7405-91c6-42ef-8810-31723830d026.xml#96ce7405-91c6-42ef-8810-31723830d026"/>
  </children>
  <children
      xsi:type="archimate:DiagramModelArchimateObject"
      id="debd08f2-76be-4f34-9bfa-d5d0212ca437">
    <sourceConnections
        xsi:type="archimate:DiagramModelArchimateConnection"
        id="820232b1-ec9a-4c84-b8c9-d5e28811ae71"
        source="debd08f2-76be-4f34-9bfa-d5d0212ca437"
        target="b1a8387f-4bc5-4d6d-8e9d-a2ddfc22c40c">
      <archimateRelationship
          xsi:type="archimate:RealizationRelationship"
          href="RealizationRelationship_ce9f61d3-fd27-4f2d-929e-029634801b59.xml#ce9f61d3-fd27-4f2d-929e-029634801b59"/>
    </sourceConnections>
    <bounds
        x="348"
        y="24"
        width="301"
        height="205"/>
    <children
        xsi:type="archimate:DiagramModelNote"
        id="40dc8e42-c461-4983-9c8f-beee730b25ba"
        textAlignment="1"
        content="AFBS-VRS-RWEB1&#xD;&#xA;&#xD;&#xA;">
      <bounds
          x="24"
          y="48"
          width="109"
          height="34"/>
    </children>
    <children
        xsi:type="archimate:DiagramModelNote"
        id="e4111c6e-5e9a-4df4-88ba-32049d1bdd00"
        textAlignment="1"
        content="10.2.2.179">
      <bounds
          x="156"
          y="48"
          width="109"
          height="34"/>
    </children>
    <children
        xsi:type="archimate:DiagramModelArchimateObject"
        id="ed6912a0-2d48-4828-931c-28cda8b9fda9">
      <bounds
          x="24"
          y="96"
          width="109"
          height="37"/>
      <archimateElement
          xsi:type="archimate:SystemSoftware"
          href="SystemSoftware_4059a0da-88ba-4cee-bc0a-b8e325d833dd.xml#4059a0da-88ba-4cee-bc0a-b8e325d833dd"/>
    </children>
    <children
        xsi:type="archimate:DiagramModelArchimateObject"
        id="cae74ac3-f6c7-4db8-a030-d84fdf7943e9"
        type="1">
      <bounds
          x="157"
          y="96"
          width="108"
          height="37"/>
      <archimateElement
          xsi:type="archimate:ApplicationComponent"
          href="ApplicationComponent_25e874cd-a0af-460c-a9f9-837539931ae3.xml#25e874cd-a0af-460c-a9f9-837539931ae3"/>
    </children>
    <children
        xsi:type="archimate:DiagramModelArchimateObject"
        id="b1a8387f-4bc5-4d6d-8e9d-a2ddfc22c40c"
        targetConnections="820232b1-ec9a-4c84-b8c9-d5e28811ae71"
        type="1">
      <bounds
          x="157"
          y="144"
          width="108"
          height="37"/>
      <archimateElement
          xsi:type="archimate:ApplicationComponent"
          href="ApplicationComponent_f0cd4e4a-b787-47b3-9570-5f98a9d5267c.xml#f0cd4e4a-b787-47b3-9570-5f98a9d5267c"/>
    </children>
    <children
        xsi:type="archimate:DiagramModelArchimateObject"
        id="31d1f248-eeee-4886-b48b-ac8b90e33727"
        type="1">
      <bounds
          x="25"
          y="144"
          width="108"
          height="37"/>
      <archimateElement
          xsi:type="archimate:ApplicationComponent"
          href="ApplicationComponent_faac0f0d-6a55-43ba-b25b-efa0d40fb64e.xml#faac0f0d-6a55-43ba-b25b-efa0d40fb64e"/>
    </children>
    <archimateElement
        xsi:type="archimate:Node"
        href="Node_1fea28e1-2cd8-406e-956d-3b95f98bac32.xml#1fea28e1-2cd8-406e-956d-3b95f98bac32"/>
  </children>
  <children
      xsi:type="archimate:DiagramModelArchimateObject"
      id="c3b1ab5a-c423-4fd0-9943-65aab15168ac">
    <bounds
        x="672"
        y="24"
        width="301"
        height="253"/>
    <children
        xsi:type="archimate:DiagramModelNote"
        id="994e081f-d179-4532-9f63-becea507764d"
        textAlignment="1"
        content="AFBS-VRSSQL-R1&#xD;&#xA;&#xD;&#xA;">
      <bounds
          x="24"
          y="48"
          width="109"
          height="34"/>
    </children>
    <children
        xsi:type="archimate:DiagramModelNote"
        id="9f560d58-4c8a-483f-89f6-302141258e66"
        textAlignment="1"
        content="10.2.2.175">
      <bounds
          x="156"
          y="48"
          width="109"
          height="34"/>
    </children>
    <children
        xsi:type="archimate:DiagramModelArchimateObject"
        id="dd29405e-d8fe-4d40-81f9-b58f9b32bf5e">
      <bounds
          x="24"
          y="96"
          width="109"
          height="37"/>
      <archimateElement
          xsi:type="archimate:SystemSoftware"
          href="SystemSoftware_4059a0da-88ba-4cee-bc0a-b8e325d833dd.xml#4059a0da-88ba-4cee-bc0a-b8e325d833dd"/>
    </children>
    <children
        xsi:type="archimate:DiagramModelArchimateObject"
        id="5685fc69-d8b0-499f-868b-ab5d5e84ef42"
        type="1">
      <bounds
          x="156"
          y="144"
          width="109"
          height="37"/>
      <archimateElement
          xsi:type="archimate:ApplicationComponent"
          href="ApplicationComponent_ed01c900-b195-405f-98e7-8cb9e077bc8c.xml#ed01c900-b195-405f-98e7-8cb9e077bc8c"/>
    </children>
    <children
        xsi:type="archimate:DiagramModelArchimateObject"
        id="663428d6-e57e-4aa4-8c9a-aac5f9576a77"
        type="1">
      <bounds
          x="156"
          y="96"
          width="109"
          height="37"/>
      <archimateElement
          xsi:type="archimate:ApplicationComponent"
          href="ApplicationComponent_25e874cd-a0af-460c-a9f9-837539931ae3.xml#25e874cd-a0af-460c-a9f9-837539931ae3"/>
    </children>
    <children
        xsi:type="archimate:DiagramModelArchimateObject"
        id="f8245be4-14ee-4cd1-89fc-95ae87550411"
        type="1">
      <bounds
          x="24"
          y="144"
          width="109"
          height="37"/>
      <archimateElement
          xsi:type="archimate:ApplicationComponent"
          href="ApplicationComponent_bfaacba1-1a17-4da9-b782-fe27fc8d6106.xml#bfaacba1-1a17-4da9-b782-fe27fc8d6106"/>
    </children>
    <children
        xsi:type="archimate:DiagramModelArchimateObject"
        id="c3863339-aa01-4d09-892b-4f914671e5be"
        type="1">
      <bounds
          x="24"
          y="192"
          width="109"
          height="37"/>
      <archimateElement
          xsi:type="archimate:ApplicationComponent"
          href="ApplicationComponent_cc023a0d-515a-4f7c-a2b2-43dd4381e2b5.xml#cc023a0d-515a-4f7c-a2b2-43dd4381e2b5"/>
    </children>
    <archimateElement
        xsi:type="archimate:Node"
        href="Node_ac9683c1-ce0f-4b32-9c1c-063800c79b8f.xml#ac9683c1-ce0f-4b32-9c1c-063800c79b8f"/>
  </children>
  <children
      xsi:type="archimate:DiagramModelArchimateObject"
      id="7208e0b2-a248-41fd-a4ac-921221251ac2">
    <sourceConnections
        xsi:type="archimate:DiagramModelArchimateConnection"
        id="e9155a7e-ce68-4ac1-b722-f2630370a66d"
        source="7208e0b2-a248-41fd-a4ac-921221251ac2"
        target="5cfa3b73-d748-4719-891f-6a549d28403b">
      <archimateRelationship
          xsi:type="archimate:RealizationRelationship"
          href="RealizationRelationship_f78e5a6f-af03-4333-861c-7252f9dc958a.xml#f78e5a6f-af03-4333-861c-7252f9dc958a"/>
    </sourceConnections>
    <bounds
        x="996"
        y="24"
        width="301"
        height="205"/>
    <children
        xsi:type="archimate:DiagramModelNote"
        id="a211f91d-b0f8-4766-bf81-4f74cd0a3f5a"
        textAlignment="1"
        content="AFBS-VRSSQL-R2&#xD;&#xA;&#xD;&#xA;">
      <bounds
          x="24"
          y="48"
          width="109"
          height="34"/>
    </children>
    <children
        xsi:type="archimate:DiagramModelNote"
        id="56bd841d-5444-44d4-ab80-17eb4f37f89c"
        textAlignment="1"
        content="10.2.2.176">
      <bounds
          x="156"
          y="48"
          width="109"
          height="34"/>
    </children>
    <children
        xsi:type="archimate:DiagramModelArchimateObject"
        id="1b813c94-6c2b-4abf-b8c6-7a98334f8705">
      <bounds
          x="24"
          y="96"
          width="109"
          height="37"/>
      <archimateElement
          xsi:type="archimate:SystemSoftware"
          href="SystemSoftware_4059a0da-88ba-4cee-bc0a-b8e325d833dd.xml#4059a0da-88ba-4cee-bc0a-b8e325d833dd"/>
    </children>
    <children
        xsi:type="archimate:DiagramModelArchimateObject"
        id="e73c9dcb-8bec-4b58-8cc1-fde69cf74798"
        type="1">
      <bounds
          x="156"
          y="144"
          width="109"
          height="37"/>
      <archimateElement
          xsi:type="archimate:ApplicationComponent"
          href="ApplicationComponent_8b05ad06-8feb-42ed-b6e8-381206f5edde.xml#8b05ad06-8feb-42ed-b6e8-381206f5edde"/>
    </children>
    <children
        xsi:type="archimate:DiagramModelArchimateObject"
        id="5cfa3b73-d748-4719-891f-6a549d28403b"
        targetConnections="e9155a7e-ce68-4ac1-b722-f2630370a66d"
        type="1">
      <bounds
          x="24"
          y="144"
          width="109"
          height="37"/>
      <archimateElement
          xsi:type="archimate:ApplicationComponent"
          href="ApplicationComponent_ad14bb34-fb07-418e-98ad-39ecab4a02ab.xml#ad14bb34-fb07-418e-98ad-39ecab4a02ab"/>
    </children>
    <children
        xsi:type="archimate:DiagramModelArchimateObject"
        id="ded8ec1e-7370-46dc-b7da-39071067ceb3"
        type="1">
      <bounds
          x="156"
          y="96"
          width="109"
          height="37"/>
      <archimateElement
          xsi:type="archimate:ApplicationComponent"
          href="ApplicationComponent_2b49e14e-7d2d-4b74-b2e1-a4353b7ff752.xml#2b49e14e-7d2d-4b74-b2e1-a4353b7ff752"/>
    </children>
    <archimateElement
        xsi:type="archimate:Node"
        href="Node_61becca4-c829-40d1-a2f3-f3dcf024120f.xml#61becca4-c829-40d1-a2f3-f3dcf024120f"/>
  </children>
</archimate:ArchimateDiagramModel>
